whyerror/__init__.py
whyerror/cli.py
whyerror-0.0.8.dist-info/LICENSE
whyerror-0.0.8.dist-info/METADATA
whyerror-0.0.8.dist-info/WHEEL
whyerror-0.0.8.dist-info/entry_points.txt
whyerror-0.0.8.dist-info/top_level.txt
whyerror-0.0.8.dist-info/RECORD
