Metadata-Version: 2.1
Name: whyerror
Version: 0.0.8
License-File: LICENSE
Requires-Dist: google-generativeai
Requires-Dist: click
Requires-Dist: python-dotenv
Requires-Dist: keyring
